Workbook

Sheet Cálculo Interno
A1: CÁLCULO DE CUSTO E MARGEM — USO INTERNO
A2: DOCUMENTO INTERNO — NÃO ENVIAR AO CLIENTE
A4: Pressupostos (valores editáveis a azul)
A5: Custo de transporte CIF total (€) | B5: 5730
A6: N.º de carrinhos | B6: 4
A7: Transporte por carrinho (€) | B7: =B5/B6 -> 1432.5
A8: Taxa de direitos aduaneiros | B8: 0.123
A9: Desalfandegamento por unidade (€) | B9: 150
A10: Margem (markup sobre o custo) | B10: 1
A11: Taxa de IVA | B11: 0.23
A14: Modelo | B14: Mercadoria (€) | C14: Extra (descrição) | D14: Preço extra (€) | E14: Transporte/un (€) | F14: Valor CIF (€) | G14: Direitos 12,3% (€) | H14: Desalfand. (€) | I14: Custo total (€) | J14: Preço venda s/IVA (€) | K14: Preço venda c/IVA (€)
A15: VY-A2 | B15: 2452 | C15: Caixa de carga fechada c/ elevação hidráulica | D15: 482 | E15: =$B$7 -> 1432.5 | F15: =B15+D15+E15 -> 4366.5 | G15: =ROUND(F15*$B$8,2) -> 537.08 | H15: =$B$9 -> 150 | I15: =F15+G15+H15 -> 5053.58 | J15: =ROUND(I15*(1+$B$10),2) -> 10107.16 | K15: =ROUND(J15*(1+$B$11),2) -> 12431.81
A16: VY-A2+2 | B16: 2561 | C16: Caixa isotérmica com suporte | D16: 85 | E16: =$B$7 -> 1432.5 | F16: =B16+D16+E16 -> 4078.5 | G16: =ROUND(F16*$B$8,2) -> 501.66 | H16: =$B$9 -> 150 | I16: =F16+G16+H16 -> 4730.16 | J16: =ROUND(I16*(1+$B$10),2) -> 9460.32 | K16: =ROUND(J16*(1+$B$11),2) -> 11636.19
A17: VY-L4 | B17: 2860 | C17: — | D17: 0 | E17: =$B$7 -> 1432.5 | F17: =B17+D17+E17 -> 4292.5 | G17: =ROUND(F17*$B$8,2) -> 527.98 | H17: =$B$9 -> 150 | I17: =F17+G17+H17 -> 4970.48 | J17: =ROUND(I17*(1+$B$10),2) -> 9940.96 | K17: =ROUND(J17*(1+$B$11),2) -> 12227.38
A18: VY-A6 | B18: 2732 | C18: — | D18: 0 | E18: =$B$7 -> 1432.5 | F18: =B18+D18+E18 -> 4164.5 | G18: =ROUND(F18*$B$8,2) -> 512.23 | H18: =$B$9 -> 150 | I18: =F18+G18+H18 -> 4826.73 | J18: =ROUND(I18*(1+$B$10),2) -> 9653.46 | K18: =ROUND(J18*(1+$B$11),2) -> 11873.76
A19: TOTAL | F19: =SUM(F15:F18) -> 16902 | G19: =SUM(G15:G18) -> 2078.95 | H19: =SUM(H15:H18) -> 600 | I19: =SUM(I15:I18) -> 19580.95 | J19: =SUM(J15:J18) -> 39161.9 | K19: =SUM(K15:K18) -> 48169.14
H21: Custo total (4 carrinhos) | J21: =I19 -> 19580.95
H22: Preço de venda s/ IVA | J22: =J19 -> 39161.9
H23: IVA (23%) | J23: =ROUND(J19*$B$11,2) -> 9007.24
H24: Preço de venda c/ IVA | J24: =J19+J23 -> 48169.14
H25: Lucro bruto (margem) | J25: =J19-I19 -> 19580.95
A28: Nota: o PDF do fornecedor inclui um desconto de 192 € no total, NÃO aplicado neste cálculo. Para o distribuir pelos carrinhos, reduzir proporcionalmente o valor da mercadoria ou o transporte total.

Sheet Orçamento
A1: CREDIBLE LEGION UNIPESSOAL LDA | D1: ORÇAMENTO
A2: NIPC 519 512 561 · Sociedade por Quotas
A3: Rua François Guichard, n.º 128 B, 5 E · 4100-012 Porto
A4: Gerência: Catarina Pinto de Azevedo
A6: Para (Cliente) | D6: Detalhes
A7: Pauliana - Restauração Lda | D7: N.º de orçamento | E7: [ORC-2026-001]
A8: 505455633 | D8: Data | E8: 04/07/2026
A9: Rua da Fábrica, Loja 1 | D9: Validade | E9: 30 dias
A10: 4490-000 Póvoa de Varzim | D10: Condições | E10: CIF Porto
A12: N.º | B12: Descrição | C12: Qtd | D12: Preço unit. s/IVA | E12: Total s/IVA
A13: 1 | B13: Carrinho de golfe elétrico VY-A2 — 2 lugares, motor 3,5 kW, bateria de lítio 48V/150A, pneus 10'' relva, para-brisas standard. Inclui caixa de carga fechada (1650×1160×280 mm) com elevação hidráulica. | C13: 1 | D13: ='Cálculo Interno'!J15 -> 10107.16 | E13: =C13*D13 -> 10107.16
A14: 2 | B14: Carrinho de golfe elétrico VY-A2+2 — 4 lugares, motor 4 kW, bateria de lítio 48V/150A, pneus 10'' relva, para-brisas standard. Inclui caixa isotérmica com suporte. | C14: 1 | D14: ='Cálculo Interno'!J16 -> 9460.32 | E14: =C14*D14 -> 9460.32
A15: 3 | B15: Carrinho de golfe elétrico VY-L4 — 2 lugares, motor 4 kW, bateria de lítio 60V/150A, pneus 12'' relva, com câmara frigorífica. | C15: 1 | D15: ='Cálculo Interno'!J17 -> 9940.96 | E15: =C15*D15 -> 9940.96
A16: 4 | B16: Carrinho de golfe elétrico VY-A6 — 6 lugares, motor 4 kW, bateria de lítio 48V/150A, pneus 10'' relva, para-brisas standard. | C16: 1 | D16: ='Cálculo Interno'!J18 -> 9653.46 | E16: =C16*D16 -> 9653.46
A17: Subtotal s/ IVA | E17: =SUM(E13:E16) -> 39161.9
A18: IVA (23%) | E18: =ROUND(E17*'Cálculo Interno'!$B$11,2) -> 9007.24
A19: TOTAL c/ IVA | E19: =E17+E18 -> 48169.14
A21: Condições
A22: · Preços em euros. Mercadoria entregue CIF Porto (Cost, Insurance & Freight).
A23: · Prazo de entrega: cerca de 20 dias úteis após confirmação e pagamento.
A24: · Pagamento: a acordar. Validade do orçamento: 30 dias a partir da data indicada.
A25: · Valores acrescidos de IVA à taxa legal em vigor (23%).
